common/__init__.py
common/adapter.py
common/automl.py
common/automl_models/base_model.py
common/automl_models/sklearn_models.py
common/automl_models/xgboost_models.py
common/credentials.py
common/pandas_helper.py
common/sql_parser.py
dbt/adapters/layer_bigquery/__init__.py
dbt/adapters/layer_bigquery/__version__.py
dbt/adapters/layer_bigquery/connections.py
dbt/adapters/layer_bigquery/impl.py
dbt/adapters/layer_snowflake/__init__.py
dbt/adapters/layer_snowflake/__version__.py
dbt/adapters/layer_snowflake/connections.py
dbt/adapters/layer_snowflake/impl.py
dbt/include/layer_bigquery/__init__.py
dbt/include/layer_bigquery/dbt_project.yml
dbt/include/layer_snowflake/__init__.py
dbt/include/layer_snowflake/dbt_project.yml
dbt_layer-0.1.3152792218.dist-info/LICENSE
dbt_layer-0.1.3152792218.dist-info/WHEEL
dbt_layer-0.1.3152792218.dist-info/METADATA
dbt_layer-0.1.3152792218.dist-info/RECORD
