Metadata-Version: 2.1
Name: dbt-layer
Version: 0.1.3152792218
Summary: The Layer adapter plugin for dbt
Author: Layer
Author-email: info@layer.ai
Requires-Python: >=3.7.2,<3.11
Classifier: Programming Language :: Python :: 3
Classifier: Programming Language :: Python :: 3.8
Classifier: Programming Language :: Python :: 3.9
Classifier: Programming Language :: Python :: 3.10
Provides-Extra: bigquery
Provides-Extra: snowflake
Requires-Dist: dbt-bigquery (==1.2.0); extra == "bigquery"
Requires-Dist: dbt-core (==1.2.0)
Requires-Dist: dbt-snowflake (==1.2.0); extra == "snowflake"
Requires-Dist: layer (==0.10.3150493728)
Requires-Dist: matplotlib (==3.5.1)
Requires-Dist: pandas (==1.3.5)
Requires-Dist: scikit-learn (==1.0.2)
Requires-Dist: sqlparse (>=0.4.2,<0.5.0)
Requires-Dist: typing-extensions (>=4.3.0)
Requires-Dist: xgboost (==1.5.1)
